<Properties StartupConfiguration="{C43527C4-CF3B-30CC-D258-164F20FD4BEE}|">
  <MonoDevelop.Ide.Workbench ActiveDocument="Assets/Scripts/PlayerMovement.cs">
    <Files>
      <File FileName="Assets/Scripts/PlayerMovement.cs" Line="1" Column="1" />
    </Files>
    <Pads>
      <Pad Id="ProjectPad">
        <State name="__root__">
          <Node name="Bears And The Bees" expanded="True" selected="True" />
        </State>
      </Pad>
    </Pads>
  </MonoDevelop.Ide.Workbench>
  <MonoDevelop.Ide.DebuggingService.PinnedWatches />
  <MonoDevelop.Ide.Workspace ActiveConfiguration="Debug" />
  <MonoDevelop.Ide.ItemProperties.Assembly-CSharp PreferredExecutionTarget="52ccb93a-1ae4-400e-a3f0-1c585193aa35" />
  <MonoDevelop.Ide.DebuggingService.Breakpoints>
    <BreakpointStore />
  </MonoDevelop.Ide.DebuggingService.Breakpoints>
  <MultiItemStartupConfigurations />
</Properties>